<?xml version="1.0" encoding="UTF-8"?>
<teiCorpus xmlns="http://www.tei-c.org/ns/1.0" xml:id="ParlaMint-CZ" xml:lang="cs">
   <teiHeader>
      <fileDesc>
         <titleStmt>
            <title type="main" xml:lang="cs">Český parlamentní korpus ParlaMint-CZ [ParlaMint]</title>
            <title type="main" xml:lang="en">Czech parliamentary corpus ParlaMint-CZ [ParlaMint]</title>
            <title type="sub" xml:lang="cs">Parlament České republiky, Poslanecká sněmovna</title>
            <title type="sub" xml:lang="en">Parliament of the Czech Republic, Chamber of Deputies</title>
            <meeting ana="#parla.term #parla.lower #parliament.PSP7" n="ps2013">ps2013</meeting>
            <meeting ana="#parla.term #parla.lower #parliament.PSP8" n="ps2017">ps2017</meeting>
            <meeting ana="#parla.term #parla.lower #parliament.PSP9" n="ps2021">ps2021</meeting>
            <respStmt>
               <persName ref="https://orcid.org/0000-0001-7953-8783">Matyáš Kopp</persName>
               <resp xml:lang="en">TEI XML corpus encoding</resp>
            </respStmt>
            <funder>
               <orgName xml:lang="en">CLARIN research infrastructure</orgName>
               <orgName xml:lang="cs">Výzkumná infrastruktura CLARIN</orgName>
            </funder>
            <funder>
               <orgName xml:lang="cs">LINDAT/CLARIAH-CZ: Digitální výzkumná infrastruktura pro jazykové technologie, umění a humanitní vědy</orgName>
               <orgName xml:lang="en">LINDAT/CLARIAH-CZ: Digital Research Infrastructure for Language Technologies, Arts and Humanities</orgName>
            </funder>
         </titleStmt>
         <editionStmt>
            <edition>2.0</edition>
         </editionStmt>
         <extent>
            <measure unit="speeches" quantity="1859" xml:lang="cs">1859 promluv</measure>
            <measure unit="speeches" quantity="1859" xml:lang="en">1859 speeches</measure>
            <measure unit="words" quantity="375493" xml:lang="cs">375493 slov</measure>
            <measure unit="words" quantity="375493" xml:lang="en">375493 words</measure>
         </extent>
         <publicationStmt>
            <publisher>
               <orgName xml:lang="en">CLARIN research infrastructure</orgName>
               <orgName xml:lang="cs">Výzkumná infrastruktura CLARIN</orgName>
               <ref target="https://www.clarin.eu/">www.clarin.eu</ref>
            </publisher>
            <idno type="URI">https://github.com/clarin-eric/ParlaMint</idno>
            <availability status="free">
               <licence>http://creativecommons.org/licenses/by/4.0/</licence>
               <p xml:lang="en">This work is licensed under the <ref target="http://creativecommons.org/licenses/by/4.0/">Creative Commons Attribution 4.0 International License</ref>.</p>
               <p xml:lang="cs">Toto dílo je licencováno <ref target="http://creativecommons.org/licenses/by/4.0/">Creative Commons Uveďte původ 4.0 Mezinárodní Veřejná licence</ref>.</p>
            </availability>
            <date when="2023-08-08">RELEASE_DATE</date>
         </publicationStmt>
         <sourceDesc>
            <bibl>
               <title type="main" xml:lang="cs">Parlament České republiky, Poslanecká sněmovna</title>
               <title type="main" xml:lang="en">Parliament of the Czech Republic, Chamber of Deputies</title>
               <idno type="URI" subtype="parliament">https://www.psp.cz/eknih/</idno>
               <date from="2016-04-13" to="2022-01-28">13.04.2016 - 28.01.2022</date>
            </bibl>
         </sourceDesc>
      </fileDesc>
      <encodingDesc>
         <projectDesc>
            <p xml:lang="cs">
               <ref target="https://www.clarin.eu/content/parlamint">ParlaMint</ref>
            </p>
            <p xml:lang="en">
               <ref target="https://www.clarin.eu/content/parlamint">ParlaMint</ref> is a project that aims to (1) create a multilingual set of comparable corpora of parliamentary proceedings uniformly encoded according to the <ref target="https://github.com/clarin-eric/parla-clarin">Parla-CLARIN recommendations</ref> and covering the COVID-19 pandemic from November 2019 as well as the earlier period from 2015 to serve as a reference corpus; (2) process the corpora linguistically to add Universal Dependencies syntactic structures and Named Entity annotation; (3) make the corpora available through concordancers and Parlameter; and (4) build use cases in Political Sciences and Digital Humanities based on the corpus data.</p>
         </projectDesc>
         <editorialDecl>
            <correction>
               <p xml:lang="en">No correction of source texts was performed.</p>
            </correction>
            <normalization>
               <p xml:lang="en">Text has not been normalised, except for spacing.</p>
            </normalization>
            <hyphenation>
               <p xml:lang="en">No end-of-line hyphens were present in the source.</p>
            </hyphenation>
            <quotation>
               <p xml:lang="en">Quotation marks have been left in the text and are not explicitly marked up.</p>
            </quotation>
            <segmentation>
               <p xml:lang="en">The texts are segmented into utterances (speeches) and segments (corresponding to paragraphs in the source transcription).</p>
            </segmentation>
         </editorialDecl>
         <tagsDecl>
            <namespace name="http://www.tei-c.org/ns/1.0">
               <tagUsage gi="text" occurs="50"/>
               <tagUsage gi="body" occurs="50"/>
               <tagUsage gi="div" occurs="50"/>
               <tagUsage gi="note" occurs="2433"/>
               <tagUsage gi="pb" occurs="388"/>
               <tagUsage gi="u" occurs="1859"/>
               <tagUsage gi="seg" occurs="5551"/>
               <tagUsage gi="kinesic" occurs="191"/>
               <tagUsage gi="vocal" occurs="182"/>
               <tagUsage gi="incident" occurs="1"/>
               <tagUsage gi="gap" occurs="8"/>
               <tagUsage gi="desc" occurs="382"/>
               <tagUsage gi="time" occurs="379"/>
            </namespace>
         </tagsDecl>
         <classDecl>
            <xi:include xmlns:xi="http://www.w3.org/2001/XInclude" href="ParlaMint-taxonomy-parla.legislature.xml"/>
            <xi:include xmlns:xi="http://www.w3.org/2001/XInclude" href="ParlaMint-CZ-taxonomy-meeting.parts.xml"/>
            <xi:include xmlns:xi="http://www.w3.org/2001/XInclude" href="ParlaMint-taxonomy-speaker_types.xml"/>
            <xi:include xmlns:xi="http://www.w3.org/2001/XInclude" href="ParlaMint-taxonomy-subcorpus.xml"/>
            <xi:include xmlns:xi="http://www.w3.org/2001/XInclude" href="ParlaMint-taxonomy-politicalOrientation.xml"/>
         </classDecl>
      </encodingDesc>
      <profileDesc>
         <settingDesc>
            <setting>
               <name type="org">Parlament České republiky - Poslanecká sněmovna</name>
               <name type="address">Sněmovní 176/4</name>
               <name type="city">Praha</name>
               <name type="country" key="CZ">Czech Republic</name>
               <date from="2016-04-13" to="2022-01-28">13.04.2016 - 28.01.2022</date>
            </setting>
         </settingDesc>
         <textClass>
            <catRef scheme="#ParlaMint-taxonomy-parla.legislature" target="#parla.bi #parla.lower"/>
         </textClass>
         <particDesc>
            <xi:include xmlns:xi="http://www.w3.org/2001/XInclude" href="ParlaMint-CZ-listOrg.xml"/>
            <xi:include xmlns:xi="http://www.w3.org/2001/XInclude" href="ParlaMint-CZ-listPerson.xml"/>
         </particDesc>
         <langUsage>
            <language ident="cs" xml:lang="cs">čeština</language>
            <language ident="en" xml:lang="cs">angličtina</language>
            <language ident="cs" xml:lang="en">Czech</language>
            <language ident="en" xml:lang="en">English</language>
         </langUsage>
      </profileDesc>
   </teiHeader>
   <xi:include xmlns:xi="http://www.w3.org/2001/XInclude" href="ParlaMint-CZ_2016-04-13-ps2013-044-02-000-000.xml"/>
   <xi:include xmlns:xi="http://www.w3.org/2001/XInclude" href="ParlaMint-CZ_2016-04-13-ps2013-044-02-001-157.xml"/>
   <xi:include xmlns:xi="http://www.w3.org/2001/XInclude" href="ParlaMint-CZ_2016-04-13-ps2013-044-02-002-158.xml"/>
   <xi:include xmlns:xi="http://www.w3.org/2001/XInclude" href="ParlaMint-CZ_2016-04-13-ps2013-044-02-003-159.xml"/>
   <xi:include xmlns:xi="http://www.w3.org/2001/XInclude" href="ParlaMint-CZ_2016-04-13-ps2013-044-02-004-165.xml"/>
   <xi:include xmlns:xi="http://www.w3.org/2001/XInclude" href="ParlaMint-CZ_2016-04-13-ps2013-044-02-005-156.xml"/>
   <xi:include xmlns:xi="http://www.w3.org/2001/XInclude" href="ParlaMint-CZ_2016-04-13-ps2013-044-02-006-162.xml"/>
   <xi:include xmlns:xi="http://www.w3.org/2001/XInclude" href="ParlaMint-CZ_2016-04-13-ps2013-044-02-007-163.xml"/>
   <xi:include xmlns:xi="http://www.w3.org/2001/XInclude" href="ParlaMint-CZ_2016-04-13-ps2013-044-02-008-164.xml"/>
   <xi:include xmlns:xi="http://www.w3.org/2001/XInclude" href="ParlaMint-CZ_2016-04-13-ps2013-044-02-009-046.xml"/>
   <xi:include xmlns:xi="http://www.w3.org/2001/XInclude" href="ParlaMint-CZ_2016-04-13-ps2013-044-02-010-052.xml"/>
   <xi:include xmlns:xi="http://www.w3.org/2001/XInclude" href="ParlaMint-CZ_2016-04-13-ps2013-044-02-011-048.xml"/>
   <xi:include xmlns:xi="http://www.w3.org/2001/XInclude" href="ParlaMint-CZ_2016-04-13-ps2013-044-02-012-049.xml"/>
   <xi:include xmlns:xi="http://www.w3.org/2001/XInclude" href="ParlaMint-CZ_2016-04-13-ps2013-044-02-013-114.xml"/>
   <xi:include xmlns:xi="http://www.w3.org/2001/XInclude" href="ParlaMint-CZ_2016-04-13-ps2013-044-02-014-016.xml"/>
   <xi:include xmlns:xi="http://www.w3.org/2001/XInclude" href="ParlaMint-CZ_2016-04-13-ps2013-044-02-015-018.xml"/>
   <xi:include xmlns:xi="http://www.w3.org/2001/XInclude" href="ParlaMint-CZ_2016-04-13-ps2013-044-02-016-098.xml"/>
   <xi:include xmlns:xi="http://www.w3.org/2001/XInclude" href="ParlaMint-CZ_2018-11-13-ps2017-020-09-000-000.xml"/>
   <xi:include xmlns:xi="http://www.w3.org/2001/XInclude" href="ParlaMint-CZ_2018-11-13-ps2017-020-09-001-018.xml"/>
   <xi:include xmlns:xi="http://www.w3.org/2001/XInclude" href="ParlaMint-CZ_2018-11-13-ps2017-020-09-002-012.xml"/>
   <xi:include xmlns:xi="http://www.w3.org/2001/XInclude" href="ParlaMint-CZ_2018-11-13-ps2017-020-09-003-056.xml"/>
   <xi:include xmlns:xi="http://www.w3.org/2001/XInclude" href="ParlaMint-CZ_2018-11-13-ps2017-020-09-004-010.xml"/>
   <xi:include xmlns:xi="http://www.w3.org/2001/XInclude" href="ParlaMint-CZ_2022-01-11-ps2021-006-01-000-000.xml"/>
   <xi:include xmlns:xi="http://www.w3.org/2001/XInclude" href="ParlaMint-CZ_2022-01-11-ps2021-006-01-001-001.xml"/>
   <xi:include xmlns:xi="http://www.w3.org/2001/XInclude" href="ParlaMint-CZ_2022-01-11-ps2021-006-01-002-002.xml"/>
   <xi:include xmlns:xi="http://www.w3.org/2001/XInclude" href="ParlaMint-CZ_2022-01-11-ps2021-006-01-003-003.xml"/>
   <xi:include xmlns:xi="http://www.w3.org/2001/XInclude" href="ParlaMint-CZ_2022-01-11-ps2021-006-01-004-004.xml"/>
   <xi:include xmlns:xi="http://www.w3.org/2001/XInclude" href="ParlaMint-CZ_2022-01-11-ps2021-006-01-005-005.xml"/>
   <xi:include xmlns:xi="http://www.w3.org/2001/XInclude" href="ParlaMint-CZ_2022-01-12-ps2021-006-02-000-000.xml"/>
   <xi:include xmlns:xi="http://www.w3.org/2001/XInclude" href="ParlaMint-CZ_2022-01-13-ps2021-006-03-000-000.xml"/>
   <xi:include xmlns:xi="http://www.w3.org/2001/XInclude" href="ParlaMint-CZ_2022-01-14-ps2021-006-04-000-000.xml"/>
   <xi:include xmlns:xi="http://www.w3.org/2001/XInclude" href="ParlaMint-CZ_2022-01-25-ps2021-006-05-000-000.xml"/>
   <xi:include xmlns:xi="http://www.w3.org/2001/XInclude" href="ParlaMint-CZ_2022-01-25-ps2021-006-05-002-060.xml"/>
   <xi:include xmlns:xi="http://www.w3.org/2001/XInclude" href="ParlaMint-CZ_2022-01-25-ps2021-006-05-003-061.xml"/>
   <xi:include xmlns:xi="http://www.w3.org/2001/XInclude" href="ParlaMint-CZ_2022-01-26-ps2021-006-06-000-000.xml"/>
   <xi:include xmlns:xi="http://www.w3.org/2001/XInclude" href="ParlaMint-CZ_2022-01-26-ps2021-006-06-001-061.xml"/>
   <xi:include xmlns:xi="http://www.w3.org/2001/XInclude" href="ParlaMint-CZ_2022-01-26-ps2021-006-06-002-079.xml"/>
   <xi:include xmlns:xi="http://www.w3.org/2001/XInclude" href="ParlaMint-CZ_2022-01-26-ps2021-006-06-003-037.xml"/>
   <xi:include xmlns:xi="http://www.w3.org/2001/XInclude" href="ParlaMint-CZ_2022-01-26-ps2021-006-06-004-042.xml"/>
   <xi:include xmlns:xi="http://www.w3.org/2001/XInclude" href="ParlaMint-CZ_2022-01-26-ps2021-006-06-005-043.xml"/>
   <xi:include xmlns:xi="http://www.w3.org/2001/XInclude" href="ParlaMint-CZ_2022-01-28-ps2021-006-08-000-000.xml"/>
   <xi:include xmlns:xi="http://www.w3.org/2001/XInclude" href="ParlaMint-CZ_2022-01-28-ps2021-006-08-001-082.xml"/>
   <xi:include xmlns:xi="http://www.w3.org/2001/XInclude" href="ParlaMint-CZ_2022-01-28-ps2021-006-08-002-057.xml"/>
   <xi:include xmlns:xi="http://www.w3.org/2001/XInclude" href="ParlaMint-CZ_2022-01-28-ps2021-006-08-003-058.xml"/>
   <xi:include xmlns:xi="http://www.w3.org/2001/XInclude" href="ParlaMint-CZ_2022-01-28-ps2021-006-08-004-036.xml"/>
</teiCorpus>
